Metadata-Version: 1.1
Name: Caboodle
Version: 1.0.2
Summary: A Python module for web browsing, web scraping or web automation
Home-page: https://bitbucket.org/bkvaluemeal/caboodle
Author: Justin Willis
Author-email: sirJustin.Willis@gmail.com
License: ISC License
Keywords: web browsing scraping automation
Platform: UNKNOWN
Classifier: Development Status :: 5 - Production/Stable
Classifier: Environment :: Console
Classifier: Intended Audience :: Developers
Classifier: License :: OSI Approved :: ISC License (ISCL)
Classifier: Operating System :: OS Independent
Classifier: Programming Language :: Python :: 2
Classifier: Programming Language :: Python :: 2.6
Classifier: Programming Language :: Python :: 2.7
Classifier: Programming Language :: Python :: 3
Classifier: Topic :: Other/Nonlisted Topic
